google/analytics/admin/__init__.py
google/analytics/admin/gapic_version.py
google/analytics/admin/py.typed
google/analytics/admin_v1alpha/__init__.py
google/analytics/admin_v1alpha/gapic_metadata.json
google/analytics/admin_v1alpha/gapic_version.py
google/analytics/admin_v1alpha/py.typed
google/analytics/admin_v1alpha/services/__init__.py
google/analytics/admin_v1alpha/services/analytics_admin_service/__init__.py
google/analytics/admin_v1alpha/services/analytics_admin_service/async_client.py
google/analytics/admin_v1alpha/services/analytics_admin_service/client.py
google/analytics/admin_v1alpha/services/analytics_admin_service/pagers.py
google/analytics/admin_v1alpha/services/analytics_admin_service/transports/__init__.py
google/analytics/admin_v1alpha/services/analytics_admin_service/transports/base.py
google/analytics/admin_v1alpha/services/analytics_admin_service/transports/grpc.py
google/analytics/admin_v1alpha/services/analytics_admin_service/transports/grpc_asyncio.py
google/analytics/admin_v1alpha/services/analytics_admin_service/transports/rest.py
google/analytics/admin_v1alpha/services/analytics_admin_service/transports/rest_base.py
google/analytics/admin_v1alpha/types/__init__.py
google/analytics/admin_v1alpha/types/access_report.py
google/analytics/admin_v1alpha/types/analytics_admin.py
google/analytics/admin_v1alpha/types/audience.py
google/analytics/admin_v1alpha/types/channel_group.py
google/analytics/admin_v1alpha/types/event_create_and_edit.py
google/analytics/admin_v1alpha/types/expanded_data_set.py
google/analytics/admin_v1alpha/types/resources.py
google/analytics/admin_v1alpha/types/subproperty_event_filter.py
google/analytics/admin_v1beta/__init__.py
google/analytics/admin_v1beta/gapic_metadata.json
google/analytics/admin_v1beta/gapic_version.py
google/analytics/admin_v1beta/py.typed
google/analytics/admin_v1beta/services/__init__.py
google/analytics/admin_v1beta/services/analytics_admin_service/__init__.py
google_analytics_admin-0.23.6.dist-info/LICENSE
google_analytics_admin-0.23.6.dist-info/METADATA
google_analytics_admin-0.23.6.dist-info/WHEEL
google_analytics_admin-0.23.6.dist-info/top_level.txt
google_analytics_admin-0.23.6.dist-info/RECORD
